{
    "name": "ImageAttribute",
    "fields": [
        {
            "fieldName": "imageLink",
            "fieldType": "String",
            "fieldValidateRules": [
                "required"
            ]
        }
    ],
    "relationships": [
        {
            "relationshipType": "many-to-one",
            "relationshipName": "product",
            "otherEntityName": "product",
            "otherEntityField": "productName"
        }
    ],
    "changelogDate": "20180809095349",
    "entityTableName": "image_attribute",
    "dto": "mapstruct",
    "pagination": "no",
    "service": "serviceImpl",
    "jpaMetamodelFiltering": false,
    "fluentMethods": true,
    "clientRootFolder": "",
    "applications": "*"
}